CHANGES.rst
CONTRIBUTORS.rst
MANIFEST.in
README.rst
VERSION
setup.cfg
setup.py
docs/index.rst
docs/resources/contentPython.html
src/pdfreactor/__init__.py
src/pdfreactor.plone.egg-info/PKG-INFO
src/pdfreactor.plone.egg-info/SOURCES.txt
src/pdfreactor.plone.egg-info/dependency_links.txt
src/pdfreactor.plone.egg-info/entry_points.txt
src/pdfreactor.plone.egg-info/namespace_packages.txt
src/pdfreactor.plone.egg-info/not-zip-safe
src/pdfreactor.plone.egg-info/requires.txt
src/pdfreactor.plone.egg-info/top_level.txt
src/pdfreactor/plone/__init__.py
src/pdfreactor/plone/_mixin.py
src/pdfreactor/plone/async.py
src/pdfreactor/plone/base.py
src/pdfreactor/plone/config.py
src/pdfreactor/plone/configure.zcml
src/pdfreactor/plone/controlpanel.py
src/pdfreactor/plone/interfaces.py
src/pdfreactor/plone/monitor.py
src/pdfreactor/plone/profiles.zcml
src/pdfreactor/plone/raw_api.py
src/pdfreactor/plone/setuphandlers.py
src/pdfreactor/plone/utils.py
src/pdfreactor/plone/profiles/default/controlpanel.xml
src/pdfreactor/plone/profiles/default/metadata.xml
src/pdfreactor/plone/resource/export.css
src/pdfreactor/plone/resource/mathjax2-run.js