Metadata-Version: 2.1
Name: pdfreactor.plone
Version: 1.0.4
Summary: PDFreactor integration for Plone
Home-page: UNKNOWN
Author: Tobias Herp
Author-email: tobias.herp@visaplan.com
License: MIT License
Project-URL: Source, https://github.com/visaplan/pdfreactor.plone
Project-URL: Documentation, https://pypi.org/project/pdfreactor.plone
Project-URL: Tracker, https://github.com/visaplan/pdfreactor.plone/issues
Platform: UNKNOWN
Classifier: Environment :: Web Environment
Classifier: Framework :: Plone
Classifier: Framework :: Plone :: 4.3
Classifier: Framework :: Zope2
Classifier: Programming Language :: Python
Classifier: Programming Language :: Python :: 2.7
Classifier: Programming Language :: Python :: 3.4
Classifier: Programming Language :: Python :: 3.5
Classifier: Programming Language :: Python :: 3.6
Classifier: Programming Language :: Python :: 3.7
Classifier: Intended Audience :: Developers
Classifier: Operating System :: OS Independent
Classifier: License :: OSI Approved :: MIT License
